pyVisualCrossingUK/__init__.py
pyVisualCrossingUK/api.py
pyVisualCrossingUK/const.py
pyVisualCrossingUK/data.py
pyvisualcrossinguk-0.1.16.20.dist-info/licenses/LICENSE
pyvisualcrossinguk-0.1.16.20.dist-info/METADATA
pyvisualcrossinguk-0.1.16.20.dist-info/WHEEL
pyvisualcrossinguk-0.1.16.20.dist-info/top_level.txt
pyvisualcrossinguk-0.1.16.20.dist-info/RECORD
