Metadata-Version: 2.4
Name: pyVisualCrossingUK
Version: 0.1.16.20
Summary: Gets the weather data from Visual Crossing with UK measurements
Home-page: https://github.com/cr0wm4n/pyVisualCrossingUK
Author: cr0wm4n
Author-email: crowman4pairs@hotmail.com
License: MIT
Classifier: Programming Language :: Python :: 3
Classifier: License :: OSI Approved :: MIT License
Classifier: Operating System :: OS Independent
Classifier: Development Status :: 4 - Beta
License-File: LICENSE
Dynamic: author
Dynamic: author-email
Dynamic: classifier
Dynamic: description
Dynamic: description-content-type
Dynamic: home-page
Dynamic: license
Dynamic: license-file
Dynamic: summary
